MousikoFidi-0.23.data/scripts/mousikofidi
MousikoFidi-0.23.data/scripts/mousikofidi-client
mousikofidi/__init__.py
mousikofidi/mousikofidi.py
mousikofidi/static/FA-LICENSE.txt
mousikofidi/static/OFL.txt
mousikofidi/static/PressStart2P-Regular.ttf
mousikofidi/static/fidi-420.png
mousikofidi/static/fidi-birth.png
mousikofidi/static/fidi-dec.png
mousikofidi/static/fidi-oct.png
mousikofidi/static/fidi.png
mousikofidi/static/css/fidi-nes.css
mousikofidi/static/css/fidi-nes.min.css
mousikofidi/static/css/fidi.css
mousikofidi/static/css/fidi.min.css
mousikofidi/static/css/normalize.css
mousikofidi/static/css/normalize.min.css
mousikofidi/static/css/terminal-green.css
mousikofidi/static/css/terminal-green.min.css
mousikofidi/static/css/terminal-solarized.css
mousikofidi/static/css/terminal-solarized.min.css
mousikofidi/static/css/terminal.css
mousikofidi/static/css/terminal.min.css
mousikofidi/static/css/nes/nes.css
mousikofidi/static/css/nes/nes.min.css
mousikofidi/static/css/water/dark.standalone.css
mousikofidi/static/css/water/dark.standalone.css.map
mousikofidi/static/css/water/dark.standalone.min.css
mousikofidi/static/css/water/dark.standalone.min.css.map
mousikofidi/static/css/water/light.standalone.css
mousikofidi/static/css/water/light.standalone.css.map
mousikofidi/static/css/water/light.standalone.min.css
mousikofidi/static/css/water/light.standalone.min.css.map
mousikofidi/static/fa/css/fontawesome.css
mousikofidi/static/fa/css/fontawesome.min.css
mousikofidi/static/fa/css/solid.css
mousikofidi/static/fa/css/solid.min.css
mousikofidi/static/fa/webfonts/fa-solid-900.ttf
mousikofidi/static/fa/webfonts/fa-solid-900.woff2
mousikofidi/static/js/player.js
mousikofidi/static/js/player.min.js
mousikofidi/static/js/tests.js
mousikofidi/templates/about.html
mousikofidi/templates/audio_player.html
mousikofidi/templates/audio_table_rows.html
mousikofidi/templates/base.html
mousikofidi/templates/cover-art.html
mousikofidi/templates/dir_detail.html
MousikoFidi-0.23.dist-info/LICENSE
MousikoFidi-0.23.dist-info/METADATA
MousikoFidi-0.23.dist-info/WHEEL
MousikoFidi-0.23.dist-info/top_level.txt
MousikoFidi-0.23.dist-info/RECORD
