Metadata-Version: 2.1
Name: MousikoFidi
Version: 0.23
Summary: MousikoFidi: Your Music Cloud
Home-page: https://git.sr.ht/~hristoast/mousikofidi
Author: Hristos N. Triantafillou
Author-email: me@hristos.co
License: UNKNOWN
Platform: UNKNOWN
Classifier: Development Status :: 4 - Beta
Classifier: Environment :: Web Environment
Classifier: License :: OSI Approved :: GNU General Public License v3 or later (GPLv3+)
Classifier: License :: OSI Approved
Classifier: Natural Language :: English
Classifier: Operating System :: POSIX :: Linux
Classifier: Programming Language :: JavaScript
Classifier: Programming Language :: Python
Classifier: Programming Language :: Python :: 3
Classifier: Programming Language :: Python :: 3 :: Only
Classifier: Programming Language :: Python :: 3.5
Classifier: Programming Language :: Python :: 3.6
Classifier: Programming Language :: Python :: 3.7
Classifier: Programming Language :: Python :: Implementation :: CPython
Classifier: Topic :: Internet :: WWW/HTTP
Classifier: Topic :: Internet :: WWW/HTTP :: Browsers
Classifier: Topic :: Internet :: WWW/HTTP :: Dynamic Content :: Content Management System
Classifier: Topic :: Multimedia
Classifier: Topic :: Multimedia :: Sound/Audio
Classifier: Topic :: Multimedia :: Sound/Audio :: Mixers
Classifier: Topic :: Multimedia :: Sound/Audio :: Players
Classifier: Topic :: Multimedia :: Sound/Audio :: Players :: MP3
Classifier: Topic :: Multimedia :: Video
Classifier: Topic :: Multimedia :: Video :: Display
Requires-Python: >=3.5
Requires-Dist: Flask (==1.0.3)
Requires-Dist: mutagen (==1.42.0)
Requires-Dist: uWSGI (==2.0.18)
